local_judge/__init__.py
local_judge/error_handler.py
local_judge/judge.py
local_judge/report.py
local_judge/ta_judge.py
local_judge/utils.py
local_judge/version.py
local_judge-2.7.2.dist-info/LICENSE
local_judge-2.7.2.dist-info/METADATA
local_judge-2.7.2.dist-info/WHEEL
local_judge-2.7.2.dist-info/entry_points.txt
local_judge-2.7.2.dist-info/top_level.txt
local_judge-2.7.2.dist-info/RECORD
