Metadata-Version: 2.1
Name: local-judge
Version: 2.7.2
Summary: Given source code, Makefile (or build commands), input files, and answer files then judge the program locally.
Home-page: https://github.com/aben20807/local-judge
Author: Huang Po-Hsuan
Author-email: aben20807@gmail.com
License: UNKNOWN
Platform: UNKNOWN
Requires-Python: >=3.6.0
Provides-Extra: ta
Requires-Dist: openpyxl (>=2.5.0) ; extra == 'ta'
Requires-Dist: rarfile (>=4.0) ; extra == 'ta'
